abna/__init__.py
abna-0.2.dist-info/METADATA
abna-0.2.dist-info/RECORD
abna-0.2.dist-info/WHEEL
abna-0.2.dist-info/top_level.txt
