Metadata-Version: 2.1
Name: abna
Version: 0.2
Summary: Automated retrieval of mutations from ABN Amro
Home-page: https://github.com/djc/abna
Author: Dirkjan Ochtman
Author-email: dirkjan@ochtman.nl
License: MIT
Platform: UNKNOWN
Classifier: Development Status :: 4 - Beta
Classifier: Intended Audience :: Developers
Classifier: License :: OSI Approved :: MIT License
Classifier: Operating System :: OS Independent
Classifier: Programming Language :: Python :: 2
Classifier: Programming Language :: Python :: 2.7
Classifier: Programming Language :: Python :: 3
Classifier: Programming Language :: Python :: 3.5
Classifier: Topic :: Software Development :: Libraries :: Python Modules
Requires-Dist: cryptography
Requires-Dist: requests
